README.md
setup.py
capacity/__init__.py
capacity/__version__.py
capacity/capacity.py
capacity.egg-info/PKG-INFO
capacity.egg-info/SOURCES.txt
capacity.egg-info/dependency_links.txt
capacity.egg-info/top_level.txt